{
  "analysis_id": "weekly:yokohama:2026-05-12",
  "type": "weekly",
  "store": "yokohama",
  "generated_at": "2026-05-12T22:39:59.614926+00:00",
  "period": {
    "start": "2026-05-04T16:35:17.094620+00:00",
    "end": "2026-05-12T19:55:19.959529+00:00"
  },
  "params": {
    "threshold": 0.4,
    "min_duration_minutes": 60,
    "ideal": 0.7,
    "gender_weight": 1.5,
    "occupancy_baseline": 163.04999999999995
  },
  "metrics": {
    "points_used": 961,
    "baseline_p95_total": 163.04999999999995,
    "reliability_score": 1.0
  },
  "metric_interpretations": {
    "daily_avg_count": 106.8,
    "volume_label": "\u5e73\u5e38",
    "baseline_label": "\u5927\u578b\u5e97\u30ec\u30d9\u30eb",
    "period_days": 9
  },
  "windows": [
    {
      "start": "2026-05-06T11:40:17.292103+00:00",
      "end": "2026-05-06T14:15:19.192854+00:00",
      "duration_minutes": 155.03167918333332,
      "avg_score": 0.4863347132781357
    },
    {
      "start": "2026-05-09T11:15:18.693898+00:00",
      "end": "2026-05-09T12:30:22.571814+00:00",
      "duration_minutes": 75.06463193333335,
      "avg_score": 0.6036512726144793
    }
  ],
  "top_windows": [
    {
      "start": "2026-05-09T11:15:18.693898+00:00",
      "end": "2026-05-09T12:30:22.571814+00:00",
      "duration_minutes": 75.06463193333335,
      "avg_score": 0.6036512726144793
    },
    {
      "start": "2026-05-06T11:40:17.292103+00:00",
      "end": "2026-05-06T14:15:19.192854+00:00",
      "duration_minutes": 155.03167918333332,
      "avg_score": 0.4863347132781357
    }
  ],
  "day_hour_heatmap": {
    "cells": [
      {
        "day": 0,
        "hour": 19,
        "avg_occupancy": 0.0981,
        "avg_female_ratio": 0.7281,
        "sample_count": 12
      },
      {
        "day": 0,
        "hour": 20,
        "avg_occupancy": 0.1605,
        "avg_female_ratio": 0.7455,
        "sample_count": 12
      },
      {
        "day": 0,
        "hour": 21,
        "avg_occupancy": 0.1743,
        "avg_female_ratio": 0.6931,
        "sample_count": 12
      },
      {
        "day": 0,
        "hour": 22,
        "avg_occupancy": 0.2872,
        "avg_female_ratio": 0.6651,
        "sample_count": 12
      },
      {
        "day": 0,
        "hour": 23,
        "avg_occupancy": 0.3051,
        "avg_female_ratio": 0.6926,
        "sample_count": 12
      },
      {
        "day": 0,
        "hour": 0,
        "avg_occupancy": 0.232,
        "avg_female_ratio": 0.5672,
        "sample_count": 12
      },
      {
        "day": 0,
        "hour": 1,
        "avg_occupancy": 0.3954,
        "avg_female_ratio": 0.4899,
        "sample_count": 17
      },
      {
        "day": 0,
        "hour": 2,
        "avg_occupancy": 0.3833,
        "avg_female_ratio": 0.4796,
        "sample_count": 24
      },
      {
        "day": 0,
        "hour": 3,
        "avg_occupancy": 0.2676,
        "avg_female_ratio": 0.5125,
        "sample_count": 24
      },
      {
        "day": 0,
        "hour": 4,
        "avg_occupancy": 0.2266,
        "avg_female_ratio": 0.4394,
        "sample_count": 17
      },
      {
        "day": 1,
        "hour": 19,
        "avg_occupancy": 0.1674,
        "avg_female_ratio": 0.7225,
        "sample_count": 24
      },
      {
        "day": 1,
        "hour": 20,
        "avg_occupancy": 0.3368,
        "avg_female_ratio": 0.7438,
        "sample_count": 24
      },
      {
        "day": 1,
        "hour": 21,
        "avg_occupancy": 0.537,
        "avg_female_ratio": 0.6288,
        "sample_count": 24
      },
      {
        "day": 1,
        "hour": 22,
        "avg_occupancy": 0.6449,
        "avg_female_ratio": 0.4951,
        "sample_count": 24
      },
      {
        "day": 1,
        "hour": 23,
        "avg_occupancy": 0.6342,
        "avg_female_ratio": 0.4519,
        "sample_count": 24
      },
      {
        "day": 1,
        "hour": 0,
        "avg_occupancy": 0.5799,
        "avg_female_ratio": 0.4627,
        "sample_count": 24
      },
      {
        "day": 1,
        "hour": 1,
        "avg_occupancy": 0.5571,
        "avg_female_ratio": 0.4943,
        "sample_count": 24
      },
      {
        "day": 1,
        "hour": 2,
        "avg_occupancy": 0.4628,
        "avg_female_ratio": 0.536,
        "sample_count": 24
      },
      {
        "day": 1,
        "hour": 3,
        "avg_occupancy": 0.3243,
        "avg_female_ratio": 0.5927,
        "sample_count": 23
      },
      {
        "day": 1,
        "hour": 4,
        "avg_occupancy": 0.3184,
        "avg_female_ratio": 0.5268,
        "sample_count": 12
      },
      {
        "day": 2,
        "hour": 19,
        "avg_occupancy": 0.092,
        "avg_female_ratio": 0.8519,
        "sample_count": 12
      },
      {
        "day": 2,
        "hour": 20,
        "avg_occupancy": 0.3082,
        "avg_female_ratio": 0.6778,
        "sample_count": 12
      },
      {
        "day": 2,
        "hour": 21,
        "avg_occupancy": 0.5443,
        "avg_female_ratio": 0.6075,
        "sample_count": 12
      },
      {
        "day": 2,
        "hour": 22,
        "avg_occupancy": 0.53,
        "avg_female_ratio": 0.5977,
        "sample_count": 12
      },
      {
        "day": 2,
        "hour": 23,
        "avg_occupancy": 0.4288,
        "avg_female_ratio": 0.5568,
        "sample_count": 12
      },
      {
        "day": 2,
        "hour": 0,
        "avg_occupancy": 0.1799,
        "avg_female_ratio": 0.4186,
        "sample_count": 12
      },
      {
        "day": 2,
        "hour": 1,
        "avg_occupancy": 0.1676,
        "avg_female_ratio": 0.3788,
        "sample_count": 12
      },
      {
        "day": 2,
        "hour": 2,
        "avg_occupancy": 0.0859,
        "avg_female_ratio": 0.5946,
        "sample_count": 12
      },
      {
        "day": 2,
        "hour": 3,
        "avg_occupancy": 0.0256,
        "avg_female_ratio": 0.7444,
        "sample_count": 12
      },
      {
        "day": 2,
        "hour": 4,
        "avg_occupancy": 0.0251,
        "avg_female_ratio": 0.6424,
        "sample_count": 11
      },
      {
        "day": 3,
        "hour": 19,
        "avg_occupancy": 0.0716,
        "avg_female_ratio": 0.9487,
        "sample_count": 12
      },
      {
        "day": 3,
        "hour": 20,
        "avg_occupancy": 0.1579,
        "avg_female_ratio": 0.74,
        "sample_count": 12
      },
      {
        "day": 3,
        "hour": 21,
        "avg_occupancy": 0.253,
        "avg_female_ratio": 0.6532,
        "sample_count": 12
      },
      {
        "day": 3,
        "hour": 22,
        "avg_occupancy": 0.4119,
        "avg_female_ratio": 0.5477,
        "sample_count": 12
      },
      {
        "day": 3,
        "hour": 23,
        "avg_occupancy": 0.4222,
        "avg_female_ratio": 0.4781,
        "sample_count": 12
      },
      {
        "day": 3,
        "hour": 0,
        "avg_occupancy": 0.2167,
        "avg_female_ratio": 0.3889,
        "sample_count": 12
      },
      {
        "day": 3,
        "hour": 1,
        "avg_occupancy": 0.1411,
        "avg_female_ratio": 0.4761,
        "sample_count": 12
      },
      {
        "day": 3,
        "hour": 2,
        "avg_occupancy": 0.1002,
        "avg_female_ratio": 0.4389,
        "sample_count": 12
      },
      {
        "day": 3,
        "hour": 3,
        "avg_occupancy": 0.0532,
        "avg_female_ratio": 0.5246,
        "sample_count": 12
      },
      {
        "day": 3,
        "hour": 4,
        "avg_occupancy": 0.0,
        "avg_female_ratio": 0.0,
        "sample_count": 0
      },
      {
        "day": 4,
        "hour": 19,
        "avg_occupancy": 0.0802,
        "avg_female_ratio": 0.975,
        "sample_count": 12
      },
      {
        "day": 4,
        "hour": 20,
        "avg_occupancy": 0.2152,
        "avg_female_ratio": 0.8672,
        "sample_count": 12
      },
      {
        "day": 4,
        "hour": 21,
        "avg_occupancy": 0.4314,
        "avg_female_ratio": 0.6518,
        "sample_count": 12
      },
      {
        "day": 4,
        "hour": 22,
        "avg_occupancy": 0.7753,
        "avg_female_ratio": 0.4804,
        "sample_count": 12
      },
      {
        "day": 4,
        "hour": 23,
        "avg_occupancy": 0.7927,
        "avg_female_ratio": 0.475,
        "sample_count": 12
      },
      {
        "day": 4,
        "hour": 0,
        "avg_occupancy": 0.643,
        "avg_female_ratio": 0.4294,
        "sample_count": 12
      },
      {
        "day": 4,
        "hour": 1,
        "avg_occupancy": 0.555,
        "avg_female_ratio": 0.4328,
        "sample_count": 12
      },
      {
        "day": 4,
        "hour": 2,
        "avg_occupancy": 0.5438,
        "avg_female_ratio": 0.4645,
        "sample_count": 12
      },
      {
        "day": 4,
        "hour": 3,
        "avg_occupancy": 0.4002,
        "avg_female_ratio": 0.4792,
        "sample_count": 12
      },
      {
        "day": 4,
        "hour": 4,
        "avg_occupancy": 0.1789,
        "avg_female_ratio": 0.6443,
        "sample_count": 12
      },
      {
        "day": 5,
        "hour": 19,
        "avg_occupancy": 0.1339,
        "avg_female_ratio": 0.8891,
        "sample_count": 12
      },
      {
        "day": 5,
        "hour": 20,
        "avg_occupancy": 0.4569,
        "avg_female_ratio": 0.7463,
        "sample_count": 12
      },
      {
        "day": 5,
        "hour": 21,
        "avg_occupancy": 0.8065,
        "avg_female_ratio": 0.6004,
        "sample_count": 12
      },
      {
        "day": 5,
        "hour": 22,
        "avg_occupancy": 0.9948,
        "avg_female_ratio": 0.5188,
        "sample_count": 12
      },
      {
        "day": 5,
        "hour": 23,
        "avg_occupancy": 0.9784,
        "avg_female_ratio": 0.5234,
        "sample_count": 12
      },
      {
        "day": 5,
        "hour": 0,
        "avg_occupancy": 0.7155,
        "avg_female_ratio": 0.4428,
        "sample_count": 12
      },
      {
        "day": 5,
        "hour": 1,
        "avg_occupancy": 0.7896,
        "avg_female_ratio": 0.4473,
        "sample_count": 12
      },
      {
        "day": 5,
        "hour": 2,
        "avg_occupancy": 0.6271,
        "avg_female_ratio": 0.4721,
        "sample_count": 12
      },
      {
        "day": 5,
        "hour": 3,
        "avg_occupancy": 0.4155,
        "avg_female_ratio": 0.5442,
        "sample_count": 12
      },
      {
        "day": 5,
        "hour": 4,
        "avg_occupancy": 0.3552,
        "avg_female_ratio": 0.5043,
        "sample_count": 12
      },
      {
        "day": 6,
        "hour": 19,
        "avg_occupancy": 0.1283,
        "avg_female_ratio": 0.9145,
        "sample_count": 12
      },
      {
        "day": 6,
        "hour": 20,
        "avg_occupancy": 0.2423,
        "avg_female_ratio": 0.6117,
        "sample_count": 12
      },
      {
        "day": 6,
        "hour": 21,
        "avg_occupancy": 0.3302,
        "avg_female_ratio": 0.6005,
        "sample_count": 12
      },
      {
        "day": 6,
        "hour": 22,
        "avg_occupancy": 0.3005,
        "avg_female_ratio": 0.6606,
        "sample_count": 11
      },
      {
        "day": 6,
        "hour": 23,
        "avg_occupancy": 0.2642,
        "avg_female_ratio": 0.5907,
        "sample_count": 12
      },
      {
        "day": 6,
        "hour": 0,
        "avg_occupancy": 0.2228,
        "avg_female_ratio": 0.5027,
        "sample_count": 12
      },
      {
        "day": 6,
        "hour": 1,
        "avg_occupancy": 0.1993,
        "avg_female_ratio": 0.5084,
        "sample_count": 12
      },
      {
        "day": 6,
        "hour": 2,
        "avg_occupancy": 0.0756,
        "avg_female_ratio": 0.6703,
        "sample_count": 12
      },
      {
        "day": 6,
        "hour": 3,
        "avg_occupancy": 0.0363,
        "avg_female_ratio": 0.6442,
        "sample_count": 12
      },
      {
        "day": 6,
        "hour": 4,
        "avg_occupancy": 0.0296,
        "avg_female_ratio": 0.481,
        "sample_count": 6
      }
    ],
    "hour_range": [
      19,
      20,
      21,
      22,
      23,
      0,
      1,
      2,
      3,
      4
    ],
    "day_labels_ja": [
      "\u6708",
      "\u706b",
      "\u6c34",
      "\u6728",
      "\u91d1",
      "\u571f",
      "\u65e5"
    ],
    "max_avg_occupancy": 0.9948
  },
  "next_week_recommendations": [
    {
      "day": 5,
      "day_label_ja": "\u571f",
      "hour": 22,
      "hour_label": "22:00-23:00",
      "avg_occupancy": 0.9948,
      "avg_female_ratio": 0.5188
    },
    {
      "day": 5,
      "day_label_ja": "\u571f",
      "hour": 23,
      "hour_label": "23:00-00:00",
      "avg_occupancy": 0.9784,
      "avg_female_ratio": 0.5234
    },
    {
      "day": 5,
      "day_label_ja": "\u571f",
      "hour": 21,
      "hour_label": "21:00-22:00",
      "avg_occupancy": 0.8065,
      "avg_female_ratio": 0.6004
    }
  ],
  "daily_summary": [
    {
      "date": "2026-05-04",
      "day_label_ja": "\u6708",
      "avg_occupancy": 0.489,
      "peak_occupancy": 0.7973,
      "avg_female_ratio": 0.4675,
      "sample_count": 41
    },
    {
      "date": "2026-05-05",
      "day_label_ja": "\u706b",
      "avg_occupancy": 0.7328,
      "peak_occupancy": 1.0,
      "avg_female_ratio": 0.5102,
      "sample_count": 120
    },
    {
      "date": "2026-05-06",
      "day_label_ja": "\u6c34",
      "avg_occupancy": 0.2405,
      "peak_occupancy": 0.601,
      "avg_female_ratio": 0.6068,
      "sample_count": 119
    },
    {
      "date": "2026-05-07",
      "day_label_ja": "\u6728",
      "avg_occupancy": 0.2031,
      "peak_occupancy": 0.4722,
      "avg_female_ratio": 0.5774,
      "sample_count": 108
    },
    {
      "date": "2026-05-08",
      "day_label_ja": "\u91d1",
      "avg_occupancy": 0.4616,
      "peak_occupancy": 0.8586,
      "avg_female_ratio": 0.5899,
      "sample_count": 120
    },
    {
      "date": "2026-05-09",
      "day_label_ja": "\u571f",
      "avg_occupancy": 0.6274,
      "peak_occupancy": 1.0,
      "avg_female_ratio": 0.5689,
      "sample_count": 120
    },
    {
      "date": "2026-05-10",
      "day_label_ja": "\u65e5",
      "avg_occupancy": 0.19,
      "peak_occupancy": 0.368,
      "avg_female_ratio": 0.6254,
      "sample_count": 113
    },
    {
      "date": "2026-05-11",
      "day_label_ja": "\u6708",
      "avg_occupancy": 0.1879,
      "peak_occupancy": 0.368,
      "avg_female_ratio": 0.6154,
      "sample_count": 113
    },
    {
      "date": "2026-05-12",
      "day_label_ja": "\u706b",
      "avg_occupancy": 0.1628,
      "peak_occupancy": 0.3189,
      "avg_female_ratio": 0.6315,
      "sample_count": 107
    }
  ],
  "last_week_summary": "\u5148\u9031\u306f\u706b\u66dc\u30fb\u571f\u66dc\u306b\u9ad8\u3044\u6df7\u96d1\u304c\u898b\u3089\u308c\u307e\u3057\u305f\u3002\n\n- \u706b\u66dc (5/5): \u5e73\u5747 73.3%\u3001\u30d4\u30fc\u30af\u6642 100% \u3068\u9ad8\u3044\u7a3c\u50cd\u7387\u3002\n- \u571f\u66dc (5/9): \u5e73\u5747 62.7%\u3001\u30d4\u30fc\u30af\u6642 100% \u3068\u9031\u672b\u3089\u3057\u3044\u8cd1\u308f\u3044\u3002\n- \u6708\u66dc (5/4, 5/11)\u3001\u6c34\u66dc (5/6)\u3001\u6728\u66dc (5/7)\u3001\u65e5\u66dc (5/10) \u306f\u5e73\u5747 16-48% \u3068\u6bd4\u8f03\u7684\u843d\u3061\u7740\u3044\u305f\u72b6\u6cc1\u3067\u3057\u305f\u3002\n- \u91d1\u66dc (5/8) \u306f\u5e73\u5747 46.2% \u3067\u3057\u305f\u3002",
  "next_week_forecast": "\u6765\u9031\u306f\u571f\u66dc\u306e\u591c\u3092\u4e2d\u5fc3\u306b\u6df7\u96d1\u304c\u4e88\u60f3\u3055\u308c\u307e\u3059\u3002\n\n- \u571f\u66dc: \u591c 21 \u6642\u4ee5\u964d\u306f 80% \u3092\u8d85\u3048\u308b\u6df7\u96d1\u304c\u4e88\u60f3\u3055\u308c\u300122 \u6642\u53f0\u306f\u6e80\u5e2d\u306b\u8fd1\u3044\u72b6\u614b\u306b\u306a\u308a\u305d\u3046\u3067\u3059\u3002\n- \u706b\u66dc: \u5148\u9031\u540c\u69d8\u3001\u5e73\u65e5\u306a\u304c\u3089 70% \u3092\u8d85\u3048\u308b\u6df7\u96d1\u304c\u898b\u8fbc\u307e\u308c\u307e\u3059\u3002\n- \u305d\u306e\u4ed6\u5e73\u65e5: \u5e73\u5747 20-40% \u7a0b\u5ea6\u3067\u63a8\u79fb\u3059\u308b\u3068\u898b\u3089\u308c\u307e\u3059\u3002",
  "ai_commentary": "\u5148\u9031\u306f\u706b\u66dc\u30fb\u571f\u66dc\u306b\u9ad8\u3044\u6df7\u96d1\u304c\u898b\u3089\u308c\u307e\u3057\u305f\u3002\n\n- \u706b\u66dc (5/5): \u5e73\u5747 73.3%\u3001\u30d4\u30fc\u30af\u6642 100% \u3068\u9ad8\u3044\u7a3c\u50cd\u7387\u3002\n- \u571f\u66dc (5/9): \u5e73\u5747 62.7%\u3001\u30d4\u30fc\u30af\u6642 100% \u3068\u9031\u672b\u3089\u3057\u3044\u8cd1\u308f\u3044\u3002\n- \u6708\u66dc (5/4, 5/11)\u3001\u6c34\u66dc (5/6)\u3001\u6728\u66dc (5/7)\u3001\u65e5\u66dc (5/10) \u306f\u5e73\u5747 16-48% \u3068\u6bd4\u8f03\u7684\u843d\u3061\u7740\u3044\u305f\u72b6\u6cc1\u3067\u3057\u305f\u3002\n- \u91d1\u66dc (5/8) \u306f\u5e73\u5747 46.2% \u3067\u3057\u305f\u3002\n\n\u6765\u9031\u306f\u571f\u66dc\u306e\u591c\u3092\u4e2d\u5fc3\u306b\u6df7\u96d1\u304c\u4e88\u60f3\u3055\u308c\u307e\u3059\u3002\n\n- \u571f\u66dc: \u591c 21 \u6642\u4ee5\u964d\u306f 80% \u3092\u8d85\u3048\u308b\u6df7\u96d1\u304c\u4e88\u60f3\u3055\u308c\u300122 \u6642\u53f0\u306f\u6e80\u5e2d\u306b\u8fd1\u3044\u72b6\u614b\u306b\u306a\u308a\u305d\u3046\u3067\u3059\u3002\n- \u706b\u66dc: \u5148\u9031\u540c\u69d8\u3001\u5e73\u65e5\u306a\u304c\u3089 70% \u3092\u8d85\u3048\u308b\u6df7\u96d1\u304c\u898b\u8fbc\u307e\u308c\u307e\u3059\u3002\n- \u305d\u306e\u4ed6\u5e73\u65e5: \u5e73\u5747 20-40% \u7a0b\u5ea6\u3067\u63a8\u79fb\u3059\u308b\u3068\u898b\u3089\u308c\u307e\u3059\u3002"
}
