{
  "analysis_id": "weekly:hiroshima_ag:2026-04-14",
  "type": "weekly",
  "store": "hiroshima_ag",
  "generated_at": "2026-04-14T22:11:03.718432+00:00",
  "period": {
    "start": "2026-04-06T16:30:27.415570+00:00",
    "end": "2026-04-14T19:55:17.987779+00:00"
  },
  "params": {
    "threshold": 0.4,
    "min_duration_minutes": 60,
    "ideal": 0.7,
    "gender_weight": 1.5,
    "occupancy_baseline": 52.0
  },
  "metrics": {
    "points_used": 990,
    "baseline_p95_total": 52.0,
    "reliability_score": 1.0
  },
  "windows": [
    {
      "start": "2026-04-07T10:20:22.094472+00:00",
      "end": "2026-04-07T12:35:20.492728+00:00",
      "duration_minutes": 134.97330426666667,
      "avg_score": 0.4935243328100471
    },
    {
      "start": "2026-04-10T16:25:21.020810+00:00",
      "end": "2026-04-10T18:25:20.847837+00:00",
      "duration_minutes": 119.99711711666667,
      "avg_score": 0.5538461538461539
    },
    {
      "start": "2026-04-11T17:40:21.535657+00:00",
      "end": "2026-04-11T18:50:21.016393+00:00",
      "duration_minutes": 69.9913456,
      "avg_score": 0.5136867636867637
    },
    {
      "start": "2026-04-12T12:40:18.856429+00:00",
      "end": "2026-04-12T15:10:34.045829+00:00",
      "duration_minutes": 150.25315666666665,
      "avg_score": 0.6303895595067072
    },
    {
      "start": "2026-04-12T16:10:33.985964+00:00",
      "end": "2026-04-12T17:30:24.240919+00:00",
      "duration_minutes": 79.83758258333334,
      "avg_score": 0.4666289592760181
    },
    {
      "start": "2026-04-13T10:25:16.953493+00:00",
      "end": "2026-04-13T13:25:18.713435+00:00",
      "duration_minutes": 180.02933236666667,
      "avg_score": 0.6077205748258381
    },
    {
      "start": "2026-04-13T14:50:20.368175+00:00",
      "end": "2026-04-13T15:55:18.656447+00:00",
      "duration_minutes": 64.9714712,
      "avg_score": 0.56748712998713
    },
    {
      "start": "2026-04-14T11:40:19.227637+00:00",
      "end": "2026-04-14T12:55:17.424859+00:00",
      "duration_minutes": 74.96995369999999,
      "avg_score": 0.482915521978022
    }
  ],
  "top_windows": [
    {
      "start": "2026-04-12T12:40:18.856429+00:00",
      "end": "2026-04-12T15:10:34.045829+00:00",
      "duration_minutes": 150.25315666666665,
      "avg_score": 0.6303895595067072
    },
    {
      "start": "2026-04-13T10:25:16.953493+00:00",
      "end": "2026-04-13T13:25:18.713435+00:00",
      "duration_minutes": 180.02933236666667,
      "avg_score": 0.6077205748258381
    },
    {
      "start": "2026-04-13T14:50:20.368175+00:00",
      "end": "2026-04-13T15:55:18.656447+00:00",
      "duration_minutes": 64.9714712,
      "avg_score": 0.56748712998713
    }
  ],
  "series_compact": [
    {
      "t": "2026-04-06T16:30:27.415570+00:00",
      "occupancy": 0.4423,
      "female_ratio": 0.4783
    },
    {
      "t": "2026-04-06T16:50:21.994928+00:00",
      "occupancy": 0.3077,
      "female_ratio": 0.5625
    },
    {
      "t": "2026-04-06T17:10:37.168685+00:00",
      "occupancy": 0.2115,
      "female_ratio": 0.6364
    },
    {
      "t": "2026-04-06T17:40:21.652583+00:00",
      "occupancy": 0.0385,
      "female_ratio": 0.0
    },
    {
      "t": "2026-04-06T18:05:34.687099+00:00",
      "occupancy": 0.0385,
      "female_ratio": 1.0
    },
    {
      "t": "2026-04-06T18:25:20.126719+00:00",
      "occupancy": 0.0385,
      "female_ratio": 1.0
    },
    {
      "t": "2026-04-06T18:45:23.569016+00:00",
      "occupancy": 0.0385,
      "female_ratio": 1.0
    },
    {
      "t": "2026-04-06T19:05:35.043039+00:00",
      "occupancy": 0.0385,
      "female_ratio": 1.0
    },
    {
      "t": "2026-04-06T19:25:19.063313+00:00",
      "occupancy": 0.0385,
      "female_ratio": 1.0
    },
    {
      "t": "2026-04-06T19:45:24.877140+00:00",
      "occupancy": 0.0577,
      "female_ratio": 1.0
    },
    {
      "t": "2026-04-07T10:15:22.009992+00:00",
      "occupancy": 0.2692,
      "female_ratio": 1.0
    },
    {
      "t": "2026-04-07T10:40:23.872706+00:00",
      "occupancy": 0.4038,
      "female_ratio": 0.9524
    },
    {
      "t": "2026-04-07T11:00:50.466122+00:00",
      "occupancy": 0.3462,
      "female_ratio": 0.9444
    },
    {
      "t": "2026-04-07T11:20:21.518474+00:00",
      "occupancy": 0.3846,
      "female_ratio": 0.85
    },
    {
      "t": "2026-04-07T11:40:22.681372+00:00",
      "occupancy": 0.4808,
      "female_ratio": 0.64
    },
    {
      "t": "2026-04-07T12:00:49.265105+00:00",
      "occupancy": 0.4423,
      "female_ratio": 0.6087
    },
    {
      "t": "2026-04-07T12:20:22.952868+00:00",
      "occupancy": 0.4423,
      "female_ratio": 0.6087
    },
    {
      "t": "2026-04-07T12:40:22.441966+00:00",
      "occupancy": 0.3846,
      "female_ratio": 0.65
    },
    {
      "t": "2026-04-07T13:01:22.594843+00:00",
      "occupancy": 0.3846,
      "female_ratio": 0.6
    },
    {
      "t": "2026-04-07T13:25:20.768925+00:00",
      "occupancy": 0.3846,
      "female_ratio": 0.5
    },
    {
      "t": "2026-04-07T13:45:24.001073+00:00",
      "occupancy": 0.4038,
      "female_ratio": 0.5238
    },
    {
      "t": "2026-04-07T14:05:31.246492+00:00",
      "occupancy": 0.4423,
      "female_ratio": 0.5652
    },
    {
      "t": "2026-04-07T14:25:20.165311+00:00",
      "occupancy": 0.4423,
      "female_ratio": 0.5652
    },
    {
      "t": "2026-04-07T14:45:23.260824+00:00",
      "occupancy": 0.4038,
      "female_ratio": 0.5238
    },
    {
      "t": "2026-04-07T15:05:32.295726+00:00",
      "occupancy": 0.4038,
      "female_ratio": 0.4286
    },
    {
      "t": "2026-04-07T15:25:19.681157+00:00",
      "occupancy": 0.4423,
      "female_ratio": 0.5652
    },
    {
      "t": "2026-04-07T15:50:22.949408+00:00",
      "occupancy": 0.5192,
      "female_ratio": 0.5556
    },
    {
      "t": "2026-04-07T16:10:36.791550+00:00",
      "occupancy": 0.3269,
      "female_ratio": 0.7059
    },
    {
      "t": "2026-04-07T16:30:30.505014+00:00",
      "occupancy": 0.3654,
      "female_ratio": 0.7368
    },
    {
      "t": "2026-04-07T16:50:22.649642+00:00",
      "occupancy": 0.25,
      "female_ratio": 0.6154
    },
    {
      "t": "2026-04-07T17:10:36.850580+00:00",
      "occupancy": 0.25,
      "female_ratio": 0.6154
    },
    {
      "t": "2026-04-07T17:30:29.520625+00:00",
      "occupancy": 0.25,
      "female_ratio": 0.6154
    },
    {
      "t": "2026-04-07T17:50:23.666481+00:00",
      "occupancy": 0.1538,
      "female_ratio": 1.0
    },
    {
      "t": "2026-04-07T18:15:25.315714+00:00",
      "occupancy": 0.1154,
      "female_ratio": 1.0
    },
    {
      "t": "2026-04-07T18:35:20.497645+00:00",
      "occupancy": 0.0769,
      "female_ratio": 1.0
    },
    {
      "t": "2026-04-07T18:55:20.796512+00:00",
      "occupancy": 0.0385,
      "female_ratio": 1.0
    },
    {
      "t": "2026-04-07T19:15:25.163170+00:00",
      "occupancy": 0.0385,
      "female_ratio": 1.0
    },
    {
      "t": "2026-04-07T19:35:19.846956+00:00",
      "occupancy": 0.0385,
      "female_ratio": 1.0
    },
    {
      "t": "2026-04-07T19:55:21.174741+00:00",
      "occupancy": 0.0385,
      "female_ratio": 1.0
    },
    {
      "t": "2026-04-08T10:15:23.452461+00:00",
      "occupancy": 0.1346,
      "female_ratio": 1.0
    },
    {
      "t": "2026-04-08T10:40:22.483563+00:00",
      "occupancy": 0.1346,
      "female_ratio": 1.0
    },
    {
      "t": "2026-04-08T11:00:55.256229+00:00",
      "occupancy": 0.1731,
      "female_ratio": 0.7778
    },
    {
      "t": "2026-04-08T11:20:21.938978+00:00",
      "occupancy": 0.1154,
      "female_ratio": 0.6667
    },
    {
      "t": "2026-04-08T11:50:24.652871+00:00",
      "occupancy": 0.0385,
      "female_ratio": 1.0
    },
    {
      "t": "2026-04-08T12:10:47.656554+00:00",
      "occupancy": 0.0385,
      "female_ratio": 1.0
    },
    {
      "t": "2026-04-08T12:30:30.558647+00:00",
      "occupancy": 0.0577,
      "female_ratio": 1.0
    },
    {
      "t": "2026-04-08T12:50:26.223234+00:00",
      "occupancy": 0.2308,
      "female_ratio": 0.25
    },
    {
      "t": "2026-04-08T13:10:39.756843+00:00",
      "occupancy": 0.2692,
      "female_ratio": 0.3571
    },
    {
      "t": "2026-04-08T13:35:21.599674+00:00",
      "occupancy": 0.25,
      "female_ratio": 0.3846
    },
    {
      "t": "2026-04-08T13:55:24.463248+00:00",
      "occupancy": 0.4808,
      "female_ratio": 0.52
    },
    {
      "t": "2026-04-08T14:15:25.213210+00:00",
      "occupancy": 0.4615,
      "female_ratio": 0.625
    },
    {
      "t": "2026-04-08T14:35:22.527087+00:00",
      "occupancy": 0.4808,
      "female_ratio": 0.56
    },
    {
      "t": "2026-04-08T14:55:21.626854+00:00",
      "occupancy": 0.3269,
      "female_ratio": 0.5882
    },
    {
      "t": "2026-04-08T15:15:23.217578+00:00",
      "occupancy": 0.3269,
      "female_ratio": 0.5882
    },
    {
      "t": "2026-04-08T15:35:19.971963+00:00",
      "occupancy": 0.3846,
      "female_ratio": 0.8
    },
    {
      "t": "2026-04-08T16:03:15.147723+00:00",
      "occupancy": 0.3846,
      "female_ratio": 0.8
    },
    {
      "t": "2026-04-08T16:20:23.404888+00:00",
      "occupancy": 0.3846,
      "female_ratio": 0.7
    },
    {
      "t": "2026-04-08T16:40:22.769467+00:00",
      "occupancy": 0.2885,
      "female_ratio": 0.6
    },
    {
      "t": "2026-04-08T17:00:49.101574+00:00",
      "occupancy": 0.2308,
      "female_ratio": 0.5
    },
    {
      "t": "2026-04-08T17:20:23.009245+00:00",
      "occupancy": 0.2692,
      "female_ratio": 0.5714
    },
    {
      "t": "2026-04-08T17:40:23.175682+00:00",
      "occupancy": 0.1923,
      "female_ratio": 0.6
    },
    {
      "t": "2026-04-08T18:00:51.380889+00:00",
      "occupancy": 0.0962,
      "female_ratio": 0.8
    },
    {
      "t": "2026-04-08T18:25:19.440202+00:00",
      "occupancy": 0.1731,
      "female_ratio": 0.6667
    },
    {
      "t": "2026-04-08T18:45:24.531273+00:00",
      "occupancy": 0.1346,
      "female_ratio": 0.5714
    },
    {
      "t": "2026-04-08T19:05:42.292640+00:00",
      "occupancy": 0.0769,
      "female_ratio": 1.0
    },
    {
      "t": "2026-04-08T19:25:20.279077+00:00",
      "occupancy": 0.0769,
      "female_ratio": 1.0
    },
    {
      "t": "2026-04-08T19:45:22.416598+00:00",
      "occupancy": 0.0769,
      "female_ratio": 1.0
    },
    {
      "t": "2026-04-09T10:05:33.343456+00:00",
      "occupancy": 0.1538,
      "female_ratio": 0.75
    },
    {
      "t": "2026-04-09T10:25:20.690175+00:00",
      "occupancy": 0.1731,
      "female_ratio": 0.7778
    },
    {
      "t": "2026-04-09T10:50:21.529936+00:00",
      "occupancy": 0.1346,
      "female_ratio": 0.7143
    },
    {
      "t": "2026-04-09T11:10:39.878126+00:00",
      "occupancy": 0.1731,
      "female_ratio": 0.6667
    },
    {
      "t": "2026-04-09T11:30:28.361351+00:00",
      "occupancy": 0.1538,
      "female_ratio": 0.625
    },
    {
      "t": "2026-04-09T11:50:20.972549+00:00",
      "occupancy": 0.1538,
      "female_ratio": 0.625
    },
    {
      "t": "2026-04-09T12:10:34.554903+00:00",
      "occupancy": 0.1538,
      "female_ratio": 0.625
    },
    {
      "t": "2026-04-09T12:30:30.721697+00:00",
      "occupancy": 0.1923,
      "female_ratio": 0.5
    },
    {
      "t": "2026-04-09T12:50:23.186795+00:00",
      "occupancy": 0.0962,
      "female_ratio": 0.4
    },
    {
      "t": "2026-04-09T13:10:36.415673+00:00",
      "occupancy": 0.1154,
      "female_ratio": 0.8333
    },
    {
      "t": "2026-04-09T13:35:19.578552+00:00",
      "occupancy": 0.0962,
      "female_ratio": 0.6
    },
    {
      "t": "2026-04-09T13:55:21.196961+00:00",
      "occupancy": 0.0577,
      "female_ratio": 1.0
    },
    {
      "t": "2026-04-09T14:15:23.466455+00:00",
      "occupancy": 0.1154,
      "female_ratio": 0.5
    },
    {
      "t": "2026-04-09T14:35:20.009343+00:00",
      "occupancy": 0.1346,
      "female_ratio": 0.5714
    },
    {
      "t": "2026-04-09T14:55:20.438407+00:00",
      "occupancy": 0.1346,
      "female_ratio": 0.5714
    },
    {
      "t": "2026-04-09T15:15:22.040472+00:00",
      "occupancy": 0.0192,
      "female_ratio": 1.0
    },
    {
      "t": "2026-04-09T15:35:19.824757+00:00",
      "occupancy": 0.0577,
      "female_ratio": 1.0
    },
    {
      "t": "2026-04-09T16:03:14.274973+00:00",
      "occupancy": 0.1154,
      "female_ratio": 0.5
    },
    {
      "t": "2026-04-09T16:20:21.694719+00:00",
      "occupancy": 0.1346,
      "female_ratio": 1.0
    },
    {
      "t": "2026-04-09T16:40:21.549993+00:00",
      "occupancy": 0.1538,
      "female_ratio": 0.625
    },
    {
      "t": "2026-04-09T17:00:48.096346+00:00",
      "occupancy": 0.1154,
      "female_ratio": 0.6667
    },
    {
      "t": "2026-04-09T17:20:21.498703+00:00",
      "occupancy": 0.1154,
      "female_ratio": 0.6667
    },
    {
      "t": "2026-04-09T17:40:22.082399+00:00",
      "occupancy": 0.0769,
      "female_ratio": 0.5
    },
    {
      "t": "2026-04-09T18:00:51.422295+00:00",
      "occupancy": 0.0769,
      "female_ratio": 0.5
    },
    {
      "t": "2026-04-09T18:55:18.453897+00:00",
      "occupancy": 0.0385,
      "female_ratio": 1.0
    },
    {
      "t": "2026-04-09T19:15:24.896130+00:00",
      "occupancy": 0.0385,
      "female_ratio": 1.0
    },
    {
      "t": "2026-04-09T19:35:19.983571+00:00",
      "occupancy": 0.0385,
      "female_ratio": 1.0
    },
    {
      "t": "2026-04-09T19:55:20.310610+00:00",
      "occupancy": 0.0385,
      "female_ratio": 1.0
    },
    {
      "t": "2026-04-10T10:15:26.390174+00:00",
      "occupancy": 0.1923,
      "female_ratio": 1.0
    },
    {
      "t": "2026-04-10T10:35:20.833456+00:00",
      "occupancy": 0.2308,
      "female_ratio": 1.0
    },
    {
      "t": "2026-04-10T10:55:22.621541+00:00",
      "occupancy": 0.2692,
      "female_ratio": 1.0
    },
    {
      "t": "2026-04-10T11:20:20.744186+00:00",
      "occupancy": 0.2885,
      "female_ratio": 0.8667
    },
    {
      "t": "2026-04-10T11:40:22.193866+00:00",
      "occupancy": 0.3654,
      "female_ratio": 0.6842
    },
    {
      "t": "2026-04-10T12:00:52.100198+00:00",
      "occupancy": 0.3654,
      "female_ratio": 0.6842
    },
    {
      "t": "2026-04-10T12:20:21.821094+00:00",
      "occupancy": 0.4615,
      "female_ratio": 0.4583
    },
    {
      "t": "2026-04-10T12:40:24.384169+00:00",
      "occupancy": 0.5192,
      "female_ratio": 0.5185
    },
    {
      "t": "2026-04-10T13:03:15.001392+00:00",
      "occupancy": 0.5577,
      "female_ratio": 0.6207
    },
    {
      "t": "2026-04-10T13:20:21.768357+00:00",
      "occupancy": 0.5577,
      "female_ratio": 0.6207
    },
    {
      "t": "2026-04-10T13:40:22.094154+00:00",
      "occupancy": 0.7308,
      "female_ratio": 0.6842
    },
    {
      "t": "2026-04-10T14:05:35.491158+00:00",
      "occupancy": 0.8269,
      "female_ratio": 0.5116
    },
    {
      "t": "2026-04-10T14:25:18.977002+00:00",
      "occupancy": 0.9615,
      "female_ratio": 0.44
    },
    {
      "t": "2026-04-10T14:45:22.052206+00:00",
      "occupancy": 0.9231,
      "female_ratio": 0.375
    },
    {
      "t": "2026-04-10T15:05:38.240995+00:00",
      "occupancy": 0.8462,
      "female_ratio": 0.4545
    },
    {
      "t": "2026-04-10T15:25:18.569504+00:00",
      "occupancy": 0.8462,
      "female_ratio": 0.4545
    },
    {
      "t": "2026-04-10T15:45:23.673405+00:00",
      "occupancy": 1.0,
      "female_ratio": 0.4286
    },
    {
      "t": "2026-04-10T16:05:35.141693+00:00",
      "occupancy": 0.9423,
      "female_ratio": 0.4694
    },
    {
      "t": "2026-04-10T16:30:29.383317+00:00",
      "occupancy": 0.7692,
      "female_ratio": 0.625
    },
    {
      "t": "2026-04-10T16:50:21.888639+00:00",
      "occupancy": 0.6346,
      "female_ratio": 0.5758
    },
    {
      "t": "2026-04-10T17:10:38.395677+00:00",
      "occupancy": 0.5577,
      "female_ratio": 0.5862
    },
    {
      "t": "2026-04-10T17:30:30.982857+00:00",
      "occupancy": 0.5769,
      "female_ratio": 0.5667
    },
    {
      "t": "2026-04-10T17:50:22.327531+00:00",
      "occupancy": 0.6731,
      "female_ratio": 0.6286
    },
    {
      "t": "2026-04-10T18:10:35.637742+00:00",
      "occupancy": 0.5769,
      "female_ratio": 0.6667
    },
    {
      "t": "2026-04-10T18:30:31.704899+00:00",
      "occupancy": 0.3077,
      "female_ratio": 0.6875
    },
    {
      "t": "2026-04-10T18:55:19.784006+00:00",
      "occupancy": 0.3654,
      "female_ratio": 0.4737
    },
    {
      "t": "2026-04-10T19:15:24.180988+00:00",
      "occupancy": 0.3846,
      "female_ratio": 0.35
    },
    {
      "t": "2026-04-10T19:35:19.244557+00:00",
      "occupancy": 0.25,
      "female_ratio": 0.3846
    },
    {
      "t": "2026-04-10T19:55:19.336232+00:00",
      "occupancy": 0.1538,
      "female_ratio": 0.625
    },
    {
      "t": "2026-04-11T10:15:23.796910+00:00",
      "occupancy": 0.25,
      "female_ratio": 0.6154
    },
    {
      "t": "2026-04-11T10:35:19.465106+00:00",
      "occupancy": 0.2115,
      "female_ratio": 0.7273
    },
    {
      "t": "2026-04-11T10:55:19.457233+00:00",
      "occupancy": 0.3077,
      "female_ratio": 0.8125
    },
    {
      "t": "2026-04-11T11:20:27.801130+00:00",
      "occupancy": 0.6923,
      "female_ratio": 0.5556
    },
    {
      "t": "2026-04-11T11:40:26.421512+00:00",
      "occupancy": 0.7885,
      "female_ratio": 0.5366
    },
    {
      "t": "2026-04-11T12:00:50.508340+00:00",
      "occupancy": 0.6538,
      "female_ratio": 0.6176
    },
    {
      "t": "2026-04-11T12:20:23.000132+00:00",
      "occupancy": 0.7692,
      "female_ratio": 0.575
    },
    {
      "t": "2026-04-11T12:40:22.205344+00:00",
      "occupancy": 1.0,
      "female_ratio": 0.5345
    },
    {
      "t": "2026-04-11T13:03:12.918606+00:00",
      "occupancy": 1.0,
      "female_ratio": 0.5714
    },
    {
      "t": "2026-04-11T13:20:23.996139+00:00",
      "occupancy": 1.0,
      "female_ratio": 0.5079
    },
    {
      "t": "2026-04-11T13:45:24.943831+00:00",
      "occupancy": 1.0,
      "female_ratio": 0.5732
    },
    {
      "t": "2026-04-11T14:05:36.710834+00:00",
      "occupancy": 1.0,
      "female_ratio": 0.6203
    },
    {
      "t": "2026-04-11T14:25:20.225793+00:00",
      "occupancy": 1.0,
      "female_ratio": 0.6301
    },
    {
      "t": "2026-04-11T14:45:22.401296+00:00",
      "occupancy": 1.0,
      "female_ratio": 0.5294
    },
    {
      "t": "2026-04-11T15:05:33.820600+00:00",
      "occupancy": 1.0,
      "female_ratio": 0.5
    },
    {
      "t": "2026-04-11T15:25:20.009503+00:00",
      "occupancy": 1.0,
      "female_ratio": 0.5
    },
    {
      "t": "2026-04-11T15:45:22.906551+00:00",
      "occupancy": 1.0,
      "female_ratio": 0.597
    },
    {
      "t": "2026-04-11T16:05:34.149783+00:00",
      "occupancy": 1.0,
      "female_ratio": 0.6
    },
    {
      "t": "2026-04-11T16:30:29.286622+00:00",
      "occupancy": 0.9038,
      "female_ratio": 0.5532
    },
    {
      "t": "2026-04-11T16:50:20.970797+00:00",
      "occupancy": 0.8269,
      "female_ratio": 0.6047
    },
    {
      "t": "2026-04-11T17:10:35.636347+00:00",
      "occupancy": 0.9038,
      "female_ratio": 0.5532
    },
    {
      "t": "2026-04-11T17:30:30.107155+00:00",
      "occupancy": 0.8269,
      "female_ratio": 0.6047
    },
    {
      "t": "2026-04-11T17:50:21.338790+00:00",
      "occupancy": 0.6923,
      "female_ratio": 0.6111
    },
    {
      "t": "2026-04-11T18:10:37.048353+00:00",
      "occupancy": 0.5769,
      "female_ratio": 0.5333
    },
    {
      "t": "2026-04-11T18:30:30.244915+00:00",
      "occupancy": 0.5,
      "female_ratio": 0.6154
    },
    {
      "t": "2026-04-11T18:55:20.018361+00:00",
      "occupancy": 0.2885,
      "female_ratio": 0.8
    },
    {
      "t": "2026-04-11T19:15:24.693816+00:00",
      "occupancy": 0.2308,
      "female_ratio": 0.8333
    },
    {
      "t": "2026-04-11T19:35:19.522735+00:00",
      "occupancy": 0.2885,
      "female_ratio": 0.8667
    },
    {
      "t": "2026-04-11T19:55:19.219763+00:00",
      "occupancy": 0.2115,
      "female_ratio": 0.8182
    },
    {
      "t": "2026-04-12T10:15:22.433984+00:00",
      "occupancy": 0.1731,
      "female_ratio": 1.0
    },
    {
      "t": "2026-04-12T10:35:19.532911+00:00",
      "occupancy": 0.1731,
      "female_ratio": 1.0
    },
    {
      "t": "2026-04-12T10:55:17.815355+00:00",
      "occupancy": 0.0962,
      "female_ratio": 1.0
    },
    {
      "t": "2026-04-12T11:20:19.721753+00:00",
      "occupancy": 0.0962,
      "female_ratio": 1.0
    },
    {
      "t": "2026-04-12T11:40:19.904869+00:00",
      "occupancy": 0.0962,
      "female_ratio": 1.0
    },
    {
      "t": "2026-04-12T12:03:13.793247+00:00",
      "occupancy": 0.0962,
      "female_ratio": 1.0
    },
    {
      "t": "2026-04-12T12:20:22.284499+00:00",
      "occupancy": 0.1346,
      "female_ratio": 1.0
    },
    {
      "t": "2026-04-12T12:40:18.856429+00:00",
      "occupancy": 0.3077,
      "female_ratio": 0.9375
    },
    {
      "t": "2026-04-12T13:00:49.425099+00:00",
      "occupancy": 0.5962,
      "female_ratio": 0.6129
    },
    {
      "t": "2026-04-12T13:20:18.792579+00:00",
      "occupancy": 0.6154,
      "female_ratio": 0.6562
    },
    {
      "t": "2026-04-12T13:45:24.128991+00:00",
      "occupancy": 0.7308,
      "female_ratio": 0.7105
    },
    {
      "t": "2026-04-12T14:05:37.226660+00:00",
      "occupancy": 0.5769,
      "female_ratio": 0.7667
    },
    {
      "t": "2026-04-12T14:25:16.923426+00:00",
      "occupancy": 0.5769,
      "female_ratio": 0.7
    },
    {
      "t": "2026-04-12T14:45:20.608801+00:00",
      "occupancy": 0.7308,
      "female_ratio": 0.5789
    },
    {
      "t": "2026-04-12T15:05:37.239200+00:00",
      "occupancy": 0.5577,
      "female_ratio": 0.5517
    },
    {
      "t": "2026-04-12T15:25:17.476941+00:00",
      "occupancy": 0.5769,
      "female_ratio": 0.5333
    },
    {
      "t": "2026-04-12T15:45:20.870514+00:00",
      "occupancy": 0.5769,
      "female_ratio": 0.5333
    },
    {
      "t": "2026-04-12T16:05:33.995499+00:00",
      "occupancy": 0.5385,
      "female_ratio": 0.4286
    },
    {
      "t": "2026-04-12T16:30:28.458932+00:00",
      "occupancy": 0.4615,
      "female_ratio": 0.625
    },
    {
      "t": "2026-04-12T16:50:22.941847+00:00",
      "occupancy": 0.5192,
      "female_ratio": 0.5926
    },
    {
      "t": "2026-04-12T17:10:37.117720+00:00",
      "occupancy": 0.4423,
      "female_ratio": 0.6087
    },
    {
      "t": "2026-04-12T17:30:24.240919+00:00",
      "occupancy": 0.4808,
      "female_ratio": 0.64
    },
    {
      "t": "2026-04-12T17:50:20.740983+00:00",
      "occupancy": 0.3462,
      "female_ratio": 0.6111
    },
    {
      "t": "2026-04-12T18:10:37.723774+00:00",
      "occupancy": 0.3654,
      "female_ratio": 0.6316
    },
    {
      "t": "2026-04-12T18:30:29.911036+00:00",
      "occupancy": 0.4231,
      "female_ratio": 0.5455
    },
    {
      "t": "2026-04-12T18:55:22.293381+00:00",
      "occupancy": 0.25,
      "female_ratio": 0.3846
    },
    {
      "t": "2026-04-12T19:15:23.677679+00:00",
      "occupancy": 0.2308,
      "female_ratio": 0.4167
    },
    {
      "t": "2026-04-12T19:35:17.264858+00:00",
      "occupancy": 0.1346,
      "female_ratio": 0.7143
    },
    {
      "t": "2026-04-12T19:55:22.425692+00:00",
      "occupancy": 0.1346,
      "female_ratio": 0.7143
    },
    {
      "t": "2026-04-13T10:15:21.206904+00:00",
      "occupancy": 0.25,
      "female_ratio": 1.0
    },
    {
      "t": "2026-04-13T10:35:21.246235+00:00",
      "occupancy": 0.2885,
      "female_ratio": 1.0
    },
    {
      "t": "2026-04-13T10:55:18.591040+00:00",
      "occupancy": 0.3269,
      "female_ratio": 1.0
    },
    {
      "t": "2026-04-13T11:20:24.867992+00:00",
      "occupancy": 0.4038,
      "female_ratio": 1.0
    },
    {
      "t": "2026-04-13T11:40:19.595853+00:00",
      "occupancy": 0.3654,
      "female_ratio": 1.0
    },
    {
      "t": "2026-04-13T12:00:50.819590+00:00",
      "occupancy": 0.3654,
      "female_ratio": 1.0
    },
    {
      "t": "2026-04-13T12:20:18.177372+00:00",
      "occupancy": 0.4038,
      "female_ratio": 1.0
    },
    {
      "t": "2026-04-13T12:40:21.091095+00:00",
      "occupancy": 0.5577,
      "female_ratio": 0.8621
    },
    {
      "t": "2026-04-13T13:03:09.689712+00:00",
      "occupancy": 0.5577,
      "female_ratio": 0.8621
    },
    {
      "t": "2026-04-13T13:20:24.247122+00:00",
      "occupancy": 0.6731,
      "female_ratio": 0.7714
    },
    {
      "t": "2026-04-13T13:45:21.089915+00:00",
      "occupancy": 0.7692,
      "female_ratio": 0.625
    },
    {
      "t": "2026-04-13T14:05:37.329888+00:00",
      "occupancy": 0.7885,
      "female_ratio": 0.5854
    },
    {
      "t": "2026-04-13T14:25:19.201792+00:00",
      "occupancy": 0.7308,
      "female_ratio": 0.6316
    },
    {
      "t": "2026-04-13T14:45:19.546549+00:00",
      "occupancy": 0.8077,
      "female_ratio": 0.5714
    },
    {
      "t": "2026-04-13T15:05:40.381361+00:00",
      "occupancy": 0.7115,
      "female_ratio": 0.6486
    },
    {
      "t": "2026-04-13T15:25:17.240747+00:00",
      "occupancy": 0.4615,
      "female_ratio": 0.6667
    },
    {
      "t": "2026-04-13T15:45:20.052812+00:00",
      "occupancy": 0.4038,
      "female_ratio": 0.7619
    },
    {
      "t": "2026-04-13T16:05:36.830441+00:00",
      "occupancy": 0.3846,
      "female_ratio": 0.6
    },
    {
      "t": "2026-04-13T16:30:28.501394+00:00",
      "occupancy": 0.4808,
      "female_ratio": 0.48
    },
    {
      "t": "2026-04-13T16:50:20.457276+00:00",
      "occupancy": 0.3462,
      "female_ratio": 0.4444
    },
    {
      "t": "2026-04-13T17:10:38.003552+00:00",
      "occupancy": 0.3077,
      "female_ratio": 0.375
    },
    {
      "t": "2026-04-13T17:30:26.936998+00:00",
      "occupancy": 0.4423,
      "female_ratio": 0.4348
    },
    {
      "t": "2026-04-13T17:50:20.535865+00:00",
      "occupancy": 0.2692,
      "female_ratio": 0.5714
    },
    {
      "t": "2026-04-13T18:10:34.804357+00:00",
      "occupancy": 0.2692,
      "female_ratio": 0.5714
    },
    {
      "t": "2026-04-13T18:30:26.007178+00:00",
      "occupancy": 0.2885,
      "female_ratio": 0.4
    },
    {
      "t": "2026-04-13T18:55:19.706864+00:00",
      "occupancy": 0.1346,
      "female_ratio": 0.8571
    },
    {
      "t": "2026-04-13T19:15:25.908711+00:00",
      "occupancy": 0.0385,
      "female_ratio": 1.0
    },
    {
      "t": "2026-04-13T19:35:22.632013+00:00",
      "occupancy": 0.0385,
      "female_ratio": 1.0
    },
    {
      "t": "2026-04-13T19:55:17.583455+00:00",
      "occupancy": 0.1154,
      "female_ratio": 0.6667
    },
    {
      "t": "2026-04-14T10:15:21.387389+00:00",
      "occupancy": 0.2692,
      "female_ratio": 1.0
    },
    {
      "t": "2026-04-14T10:35:18.798349+00:00",
      "occupancy": 0.1731,
      "female_ratio": 1.0
    },
    {
      "t": "2026-04-14T10:55:17.895843+00:00",
      "occupancy": 0.1538,
      "female_ratio": 1.0
    },
    {
      "t": "2026-04-14T11:20:20.103503+00:00",
      "occupancy": 0.1923,
      "female_ratio": 0.8
    },
    {
      "t": "2026-04-14T11:40:19.227637+00:00",
      "occupancy": 0.3654,
      "female_ratio": 0.7895
    },
    {
      "t": "2026-04-14T12:00:50.359101+00:00",
      "occupancy": 0.4038,
      "female_ratio": 0.7143
    },
    {
      "t": "2026-04-14T12:20:22.073992+00:00",
      "occupancy": 0.5385,
      "female_ratio": 0.6429
    },
    {
      "t": "2026-04-14T12:40:20.280910+00:00",
      "occupancy": 0.5,
      "female_ratio": 0.6154
    },
    {
      "t": "2026-04-14T13:03:12.297209+00:00",
      "occupancy": 0.5192,
      "female_ratio": 0.5185
    },
    {
      "t": "2026-04-14T13:20:22.358258+00:00",
      "occupancy": 0.5192,
      "female_ratio": 0.5185
    },
    {
      "t": "2026-04-14T13:45:24.126465+00:00",
      "occupancy": 0.3654,
      "female_ratio": 0.4211
    },
    {
      "t": "2026-04-14T14:05:35.351012+00:00",
      "occupancy": 0.4038,
      "female_ratio": 0.381
    },
    {
      "t": "2026-04-14T14:25:18.977396+00:00",
      "occupancy": 0.3462,
      "female_ratio": 0.3889
    },
    {
      "t": "2026-04-14T14:45:23.912035+00:00",
      "occupancy": 0.1923,
      "female_ratio": 0.2
    },
    {
      "t": "2026-04-14T15:05:34.437292+00:00",
      "occupancy": 0.1923,
      "female_ratio": 0.4
    },
    {
      "t": "2026-04-14T15:25:21.097051+00:00",
      "occupancy": 0.1154,
      "female_ratio": 0.3333
    },
    {
      "t": "2026-04-14T15:45:24.082221+00:00",
      "occupancy": 0.1538,
      "female_ratio": 0.5
    },
    {
      "t": "2026-04-14T16:05:34.826050+00:00",
      "occupancy": 0.0769,
      "female_ratio": 1.0
    },
    {
      "t": "2026-04-14T16:30:29.329815+00:00",
      "occupancy": 0.0385,
      "female_ratio": 1.0
    },
    {
      "t": "2026-04-14T16:50:20.260364+00:00",
      "occupancy": 0.0385,
      "female_ratio": 1.0
    },
    {
      "t": "2026-04-14T17:10:33.191491+00:00",
      "occupancy": 0.0769,
      "female_ratio": 1.0
    },
    {
      "t": "2026-04-14T17:30:30.653590+00:00",
      "occupancy": 0.0385,
      "female_ratio": 1.0
    },
    {
      "t": "2026-04-14T17:50:20.010977+00:00",
      "occupancy": 0.0385,
      "female_ratio": 1.0
    },
    {
      "t": "2026-04-14T18:10:37.367464+00:00",
      "occupancy": 0.0385,
      "female_ratio": 1.0
    },
    {
      "t": "2026-04-14T18:30:29.471578+00:00",
      "occupancy": 0.0385,
      "female_ratio": 1.0
    },
    {
      "t": "2026-04-14T18:55:17.928635+00:00",
      "occupancy": 0.0385,
      "female_ratio": 1.0
    },
    {
      "t": "2026-04-14T19:15:21.859941+00:00",
      "occupancy": 0.0385,
      "female_ratio": 1.0
    },
    {
      "t": "2026-04-14T19:35:20.949630+00:00",
      "occupancy": 0.0385,
      "female_ratio": 1.0
    },
    {
      "t": "2026-04-14T19:55:17.987779+00:00",
      "occupancy": 0.0769,
      "female_ratio": 0.5
    }
  ]
}
